supporter_of_the_week/__init__.py
supporter_of_the_week/supporter_of_the_week.py
supporter_of_the_week-0.1.1.dist-info/LICENSE
supporter_of_the_week-0.1.1.dist-info/METADATA
supporter_of_the_week-0.1.1.dist-info/WHEEL
supporter_of_the_week-0.1.1.dist-info/entry_points.txt
supporter_of_the_week-0.1.1.dist-info/RECORD
