Metadata-Version: 2.1
Name: supporter-of-the-week
Version: 0.1.1
Summary: Supporter of the Week project
License: GNU GPLv3
Author: Egon Rijpkema
Author-email: git@egonrijpkema.nl
Requires-Python: >=3.12,<4.0
Classifier: License :: Other/Proprietary License
Classifier: Programming Language :: Python :: 3
Classifier: Programming Language :: Python :: 3.12
Requires-Dist: icalendar (>=6.1.0,<7.0.0)
Requires-Dist: workalendar (>=17.0.0,<18.0.0)
